napari_swc_reader/__init__.py
napari_swc_reader/_reader.py
napari_swc_reader/_sample_data.py
napari_swc_reader/_version.py
napari_swc_reader/napari.yaml
napari_swc_reader/_tests/__init__.py
napari_swc_reader/_tests/test_reader.py
napari_swc_reader/_tests/test_sample_data.py
napari_swc_reader-0.1.3.dist-info/LICENSE
napari_swc_reader-0.1.3.dist-info/METADATA
napari_swc_reader-0.1.3.dist-info/WHEEL
napari_swc_reader-0.1.3.dist-info/entry_points.txt
napari_swc_reader-0.1.3.dist-info/top_level.txt
napari_swc_reader-0.1.3.dist-info/RECORD
