Metadata-Version: 2.1
Name: napari-swc-reader
Version: 0.1.3
Summary: A simple napari plugin to load swc file to napari viewer
Author: Clément Caporal
Author-email: caporal.clement@gmail.com
License: 
Project-URL: Bug Tracker, https://github.com/LaboratoryOpticsBiosciences/napari-swc-reader/issues
Project-URL: Documentation, https://github.com/LaboratoryOpticsBiosciences/napari-swc-reader#README.md
Project-URL: Source Code, https://github.com/LaboratoryOpticsBiosciences/napari-swc-reader
Project-URL: User Support, https://github.com/LaboratoryOpticsBiosciences/napari-swc-reader/issues
Classifier: Development Status :: 2 - Pre-Alpha
Classifier: Framework :: napari
Classifier: Intended Audience :: Developers
Classifier: License :: OSI Approved :: BSD License
Classifier: Operating System :: OS Independent
Classifier: Programming Language :: Python
Classifier: Programming Language :: Python :: 3
Classifier: Programming Language :: Python :: 3 :: Only
Classifier: Programming Language :: Python :: 3.9
Classifier: Programming Language :: Python :: 3.10
Classifier: Programming Language :: Python :: 3.11
Classifier: Programming Language :: Python :: 3.12
Classifier: Topic :: Scientific/Engineering :: Image Processing
Requires-Python: >=3.9
License-File: LICENSE
Requires-Dist: numpy
Requires-Dist: pandas
Provides-Extra: testing
Requires-Dist: tox; extra == "testing"
Requires-Dist: pytest; extra == "testing"
Requires-Dist: pytest-cov; extra == "testing"
